sent_dm/__init__.py
sent_dm/_base_client.py
sent_dm/_client.py
sent_dm/_compat.py
sent_dm/_constants.py
sent_dm/_exceptions.py
sent_dm/_files.py
sent_dm/_models.py
sent_dm/_qs.py
sent_dm/_resource.py
sent_dm/_response.py
sent_dm/_streaming.py
sent_dm/_types.py
sent_dm/_version.py
sent_dm/py.typed
sent_dm/_utils/__init__.py
sent_dm/_utils/_compat.py
sent_dm/_utils/_datetime_parse.py
sent_dm/_utils/_json.py
sent_dm/_utils/_logs.py
sent_dm/_utils/_proxy.py
sent_dm/_utils/_reflection.py
sent_dm/_utils/_resources_proxy.py
sent_dm/_utils/_streams.py
sent_dm/_utils/_sync.py
sent_dm/_utils/_transform.py
sent_dm/_utils/_typing.py
sent_dm/_utils/_utils.py
sent_dm/lib/.keep
sent_dm/resources/__init__.py
sent_dm/resources/contacts.py
sent_dm/resources/messages.py
sent_dm/resources/number_lookup.py
sent_dm/resources/templates.py
sent_dm/resources/organizations/__init__.py
sent_dm/resources/organizations/organizations.py
sent_dm/resources/organizations/users.py
sent_dm/types/__init__.py
sent_dm/types/contact_list_item.py
sent_dm/types/contact_list_params.py
sent_dm/types/contact_list_response.py
sent_dm/types/contact_retrieve_by_phone_params.py
sent_dm/types/contact_retrieve_id_params.py
sent_dm/types/message_retrieve_response.py
sent_dm/types/message_send_quick_message_params.py
sent_dm/types/message_send_to_contact_params.py
sent_dm/types/message_send_to_phone_params.py
sent_dm/types/number_lookup_retrieve_params.py
sent_dm/types/number_lookup_retrieve_response.py
sent_dm/types/organization_list_response.py
sent_dm/types/organization_retrieve_profiles_response.py
sent_dm/types/profile_summary.py
sent_dm/types/template_body_content.py
sent_dm/types/template_body_content_param.py
sent_dm/types/template_create_params.py
sent_dm/types/template_definition.py
sent_dm/types/template_definition_param.py
sent_dm/types/template_list_params.py
sent_dm/types/template_list_response.py
sent_dm/types/template_response.py
sent_dm/types/template_variable.py
sentdm-0.5.0.dist-info/METADATA
sentdm-0.5.0.dist-info/WHEEL
sentdm-0.5.0.dist-info/licenses/LICENSE
sentdm-0.5.0.dist-info/RECORD
